LICENSE.TXT
README.md
pyproject.toml
setup.py
datahasher/__init__.py
datahasher/config.py
datahasher/database.py
datahasher.egg-info/PKG-INFO
datahasher.egg-info/SOURCES.txt
datahasher.egg-info/dependency_links.txt
datahasher.egg-info/requires.txt
datahasher.egg-info/top_level.txt
datahasher/front/__init__.py
datahasher/front/app.py
datahasher/front/logger.py
datahasher/front/waiter.py
datahasher/front/manager/__init__.py
datahasher/front/manager/base.py
datahasher/front/manager/concept.py
datahasher/utils/__init__.py
datahasher/utils/utils_misc.py
datahasher/utils/utils_sql.py