Metadata-Version: 2.1
Name: datahasher
Version: 0.1.0
Summary: Toolkit to develop data pipelines in python
Home-page: https://github.com/gab23r/datahasher
Author: Gabriel Robin
Classifier: Programming Language :: Python :: 3
Classifier: License :: OSI Approved :: MIT License
Classifier: Operating System :: OS Independent
Requires-Python: >=3.11
Provides-Extra: front
License-File: LICENSE.TXT
